CHANGES.rst
LICENSE
MANIFEST.in
README.md
requirements.txt
setup.cfg
setup.py
test_ansi.py
doc/changes.rst
doc/conf.py
doc/index.rst
doc/requirements.txt
sphinxcontrib/__init__.py
sphinxcontrib/black-on-white.css
sphinxcontrib/tagscript.py
tagscript_ansi.egg-info/PKG-INFO
tagscript_ansi.egg-info/SOURCES.txt
tagscript_ansi.egg-info/dependency_links.txt
tagscript_ansi.egg-info/namespace_packages.txt
tagscript_ansi.egg-info/not-zip-safe
tagscript_ansi.egg-info/requires.txt
tagscript_ansi.egg-info/top_level.txt