Metadata-Version: 2.1
Name: tagscript-ansi
Version: 0.1.dev20220618
Summary: A small example package
Home-page: https://github.com/Leg3ndary/tagscript-ansi
Author: Ben Zhou
Author-email: tagscript.l@gmail.com
License: BSD
Download-URL: http://pypi.python.org/pypi/tagscript-ansi
Platform: any
Classifier: Development Status :: 4 - Beta
Classifier: Environment :: Console
Classifier: Environment :: Web Environment
Classifier: Intended Audience :: Developers
Classifier: License :: OSI Approved :: BSD License
Classifier: Operating System :: OS Independent
Classifier: Programming Language :: Python
Classifier: Topic :: Documentation
Classifier: Topic :: Utilities
License-File: LICENSE
